{"frameRate":30,"name":"ui_danger","version":"5.5","compatibleVersion":"5.5","armature":[{"type":"Armature","frameRate":30,"name":"ui_danger","aabb":{"x":22.04,"y":-387.32,"width":690.12,"height":2142.38},"bone":[{"name":"root"},{"inheritScale":false,"name":"元件 2","parent":"root","transform":{"x":-51,"y":-38.3,"scX":4.32,"scY":4.32}},{"inheritScale":false,"name":"元件 2_0","parent":"root","transform":{"x":785.2,"y":1406.05,"skX":180,"skY":180,"scX":4.32,"scY":4.32}}],"slot":[{"blendMode":"add","name":"元件 2","parent":"元件 2"},{"blendMode":"add","name":"元件 2_0","parent":"元件 2_0"}],"skin":[{"slot":[{"name":"元件 2","display":[{"name":"元件 2","transform":{"x":22,"y":-2.55}}]},{"name":"元件 2_0","display":[{"name":"元件 2","transform":{"x":22,"y":-2.55}}]}]}],"animation":[{"duration":54,"playTimes":0,"name":"ui_danger","bone":[{"name":"元件 2","translateFrame":[{"duration":4,"tweenEasing":0},{"duration":5,"tweenEasing":0,"x":-0.05,"y":55.9},{"duration":5,"tweenEasing":0,"x":-0.15,"y":125.8},{"duration":5,"tweenEasing":0,"x":-0.15,"y":195.9},{"duration":5,"tweenEasing":0,"x":-0.15,"y":265.9},{"duration":5,"tweenEasing":0,"x":-0.1,"y":336},{"duration":6,"tweenEasing":0,"x":-0.1,"y":406},{"duration":6,"tweenEasing":0,"y":490.1},{"duration":7,"tweenEasing":0,"y":574.05},{"duration":6,"tweenEasing":0,"x":-0.05,"y":671.95},{"duration":0,"y":756}]},{"name":"元件 2_0","translateFrame":[{"duration":4,"tweenEasing":0},{"duration":5,"tweenEasing":0,"x":0.05,"y":-69.6},{"duration":5,"tweenEasing":0,"x":0.15,"y":-156.7},{"duration":5,"tweenEasing":0,"x":0.2,"y":-243.85},{"duration":5,"tweenEasing":0,"x":0.2,"y":-330.85},{"duration":5,"tweenEasing":0,"x":0.25,"y":-417.95},{"duration":6,"tweenEasing":0,"x":0.2,"y":-504.95},{"duration":6,"tweenEasing":0,"x":0.2,"y":-609.35},{"duration":7,"tweenEasing":0,"x":0.15,"y":-713.7},{"duration":6,"tweenEasing":0,"x":0.1,"y":-835.45},{"duration":0,"y":-940}]}],"slot":[{"name":"元件 2","colorFrame":[{"duration":4,"tweenEasing":0,"value":{"aM":44}},{"duration":5,"tweenEasing":0},{"duration":5,"tweenEasing":0,"value":{"aM":44}},{"duration":5,"tweenEasing":0},{"duration":5,"tweenEasing":0,"value":{"aM":44}},{"duration":5,"tweenEasing":0},{"duration":6,"tweenEasing":0,"value":{"aM":44}},{"duration":6,"tweenEasing":0},{"duration":7,"tweenEasing":0,"value":{"aM":44}},{"duration":6,"tweenEasing":0},{"duration":0,"value":{"aM":44}}]},{"name":"元件 2_0","colorFrame":[{"duration":4,"tweenEasing":0,"value":{"aM":44}},{"duration":5,"tweenEasing":0},{"duration":5,"tweenEasing":0,"value":{"aM":44}},{"duration":5,"tweenEasing":0},{"duration":5,"tweenEasing":0,"value":{"aM":44}},{"duration":5,"tweenEasing":0},{"duration":6,"tweenEasing":0,"value":{"aM":44}},{"duration":6,"tweenEasing":0},{"duration":7,"tweenEasing":0,"value":{"aM":44}},{"duration":6,"tweenEasing":0},{"duration":0,"value":{"aM":44}}]}]}],"defaultActions":[{"gotoAndPlay":"ui_danger"}]}]}